[{"object": "corp_action", "ex_date": "2025-10-24", "rec_date": "2025-10-25", "kind": "dividend", "factor": null, "div_per_share": 4, "rights_ratio_n": null, "rights_ratio_m": null, "rights_premium": null, "series": "EQ", "isin": "INE00R701025", "comp": "Dalmia Bharat Limited", "face_val": "2", "subject": "Interim Dividend - Rs 4 Per Share"}, {"object": "corp_action", "ex_date": "2025-06-23", "rec_date": "2025-06-23", "kind": "meeting", "factor": null, "div_per_share": null, "rights_ratio_n": null, "rights_ratio_m": null, "rights_premium": null, "series": "EQ", "isin": "INE00R701025", "comp": "Dalmia Bharat Limited", "face_val": "2", "subject": "Annual General Meeting/Dividend - Rs 5 Per Share"}, {"object": "corp_action", "ex_date": "2024-10-25", "rec_date": "2024-10-26", "kind": "dividend", "factor": null, "div_per_share": 4, "rights_ratio_n": null, "rights_ratio_m": null, "rights_premium": null, "series": "EQ", "isin": "INE00R701025", "comp": "Dalmia Bharat Limited", "face_val": "2", "subject": "Interim Dividend - Rs 4 Per Share"}, {"object": "corp_action", "ex_date": "2024-06-19", "rec_date": "2024-06-19", "kind": "dividend", "factor": null, "div_per_share": 5, "rights_ratio_n": null, "rights_ratio_m": null, "rights_premium": null, "series": "EQ", "isin": "INE00R701025", "comp": "Dalmia Bharat Limited", "face_val": "2", "subject": "Dividend - Rs 5 Per Share"}, {"object": "corp_action", "ex_date": "2023-10-20", "rec_date": "2023-10-21", "kind": "dividend", "factor": null, "div_per_share": 4, "rights_ratio_n": null, "rights_ratio_m": null, "rights_premium": null, "series": "EQ", "isin": "INE00R701025", "comp": "Dalmia Bharat Limited", "face_val": "2", "subject": "Interim Dividend - Rs 4 Per Share"}, {"object": "corp_action", "ex_date": "2023-06-23", "rec_date": "2023-06-23", "kind": "dividend", "factor": null, "div_per_share": 5, "rights_ratio_n": null, "rights_ratio_m": null, "rights_premium": null, "series": "EQ", "isin": "INE00R701025", "comp": "Dalmia Bharat Limited", "face_val": "2", "subject": "Dividend - Rs 5 Per Share"}, {"object": "corp_action", "ex_date": "2022-11-10", "rec_date": "2022-11-11", "kind": "dividend", "factor": null, "div_per_share": 4, "rights_ratio_n": null, "rights_ratio_m": null, "rights_premium": null, "series": "EQ", "isin": "INE00R701025", "comp": "Dalmia Bharat Limited", "face_val": "2", "subject": "Interim Dividend - Rs 4 Per Share"}, {"object": "corp_action", "ex_date": "2022-06-23", "rec_date": "2022-06-25", "kind": "dividend", "factor": null, "div_per_share": 5, "rights_ratio_n": null, "rights_ratio_m": null, "rights_premium": null, "series": "EQ", "isin": "INE00R701025", "comp": "Dalmia Bharat Limited", "face_val": "2", "subject": "Dividend - Rs 5 Per Share"}, {"object": "corp_action", "ex_date": "2021-11-09", "rec_date": "2021-11-10", "kind": "dividend", "factor": null, "div_per_share": 4, "rights_ratio_n": null, "rights_ratio_m": null, "rights_premium": null, "series": "EQ", "isin": "INE00R701025", "comp": "Dalmia Bharat Limited", "face_val": "2", "subject": "Interim Dividend - Rs 4 Per Share"}, {"object": "corp_action", "ex_date": "2021-09-21", "rec_date": "2021-09-22", "kind": "meeting", "factor": null, "div_per_share": null, "rights_ratio_n": null, "rights_ratio_m": null, "rights_premium": null, "series": "EQ", "isin": "INE00R701025", "comp": "Dalmia Bharat Limited", "face_val": "2", "subject": "Annual General Meeting/Dividend - Rs 1.33 Per Share"}, {"object": "corp_action", "ex_date": "2020-09-22", "rec_date": null, "kind": "meeting", "factor": null, "div_per_share": null, "rights_ratio_n": null, "rights_ratio_m": null, "rights_premium": null, "series": "EQ", "isin": "INE00R701025", "comp": "Dalmia Bharat Limited", "face_val": "2", "subject": "Annual General Meeting"}, {"object": "corp_action", "ex_date": "2020-02-17", "rec_date": "2020-02-18", "kind": "dividend", "factor": null, "div_per_share": 2, "rights_ratio_n": null, "rights_ratio_m": null, "rights_premium": null, "series": "EQ", "isin": "INE00R701025", "comp": "Dalmia Bharat Limited", "face_val": "2", "subject": "Interim Dividend - Rs 2 Per Share"}, {"object": "corp_action", "ex_date": "2019-08-22", "rec_date": null, "kind": "meeting", "factor": null, "div_per_share": null, "rights_ratio_n": null, "rights_ratio_m": null, "rights_premium": null, "series": "EQ", "isin": "INE00R701025", "comp": "Dalmia Bharat Limited", "face_val": "2", "subject": "Annual General Meeting/Dividend - Rs 2 Per Share"}]