[{"object": "corp_action", "ex_date": "2025-06-20", "rec_date": "2025-06-20", "kind": "dividend", "factor": null, "div_per_share": 7, "rights_ratio_n": null, "rights_ratio_m": null, "rights_premium": null, "series": "EQ", "isin": "INE226A01021", "comp": "Voltas Limited", "face_val": "1", "subject": "Dividend - Rs 7 Per Share"}, {"object": "corp_action", "ex_date": "2024-06-25", "rec_date": null, "kind": "meeting", "factor": null, "div_per_share": null, "rights_ratio_n": null, "rights_ratio_m": null, "rights_premium": null, "series": "EQ", "isin": "INE226A01021", "comp": "Voltas Limited", "face_val": "1", "subject": "Annual General Meeting/Dividend - Rs 5.50 Per Share"}, {"object": "corp_action", "ex_date": "2023-06-09", "rec_date": null, "kind": "meeting", "factor": null, "div_per_share": null, "rights_ratio_n": null, "rights_ratio_m": null, "rights_premium": null, "series": "EQ", "isin": "INE226A01021", "comp": "Voltas Limited", "face_val": "1", "subject": "Annual General Meeting/Dividend - Rs 4.25 Per Share"}, {"object": "corp_action", "ex_date": "2022-06-09", "rec_date": null, "kind": "meeting", "factor": null, "div_per_share": null, "rights_ratio_n": null, "rights_ratio_m": null, "rights_premium": null, "series": "EQ", "isin": "INE226A01021", "comp": "Voltas Limited", "face_val": "1", "subject": "Annual General Meeting/Dividend - Rs 5.50 Per Share"}, {"object": "corp_action", "ex_date": "2021-08-11", "rec_date": null, "kind": "meeting", "factor": null, "div_per_share": null, "rights_ratio_n": null, "rights_ratio_m": null, "rights_premium": null, "series": "EQ", "isin": "INE226A01021", "comp": "Voltas Limited", "face_val": "1", "subject": "Annual General Meeting/Dividend - Rs 5 Per Share"}, {"object": "corp_action", "ex_date": "2020-08-05", "rec_date": null, "kind": "meeting", "factor": null, "div_per_share": null, "rights_ratio_n": null, "rights_ratio_m": null, "rights_premium": null, "series": "EQ", "isin": "INE226A01021", "comp": "Voltas Limited", "face_val": "1", "subject": "Annual General Meeting/Dividend - Rs 4 Per Share"}, {"object": "corp_action", "ex_date": "2019-07-17", "rec_date": null, "kind": "meeting", "factor": null, "div_per_share": null, "rights_ratio_n": null, "rights_ratio_m": null, "rights_premium": null, "series": "EQ", "isin": "INE226A01021", "comp": "Voltas Limited", "face_val": "1", "subject": "Annual General Meeting/ Dividend - Rs 4 Per Share"}, {"object": "corp_action", "ex_date": "2018-08-03", "rec_date": null, "kind": "meeting", "factor": null, "div_per_share": null, "rights_ratio_n": null, "rights_ratio_m": null, "rights_premium": null, "series": "EQ", "isin": "INE226A01021", "comp": "Voltas Limited", "face_val": "1", "subject": "Annual General Meeting / Dividend- Rs 4 Per Share"}, {"object": "corp_action", "ex_date": "2017-08-04", "rec_date": null, "kind": "meeting", "factor": null, "div_per_share": null, "rights_ratio_n": null, "rights_ratio_m": null, "rights_premium": null, "series": "EQ", "isin": "INE226A01021", "comp": "Voltas Limited", "face_val": "1", "subject": "Annual General Meeting/Dividend - Rs 3.50 Per Share"}, {"object": "corp_action", "ex_date": "2016-08-05", "rec_date": null, "kind": "meeting", "factor": null, "div_per_share": null, "rights_ratio_n": null, "rights_ratio_m": null, "rights_premium": null, "series": "EQ", "isin": "INE226A01021", "comp": "Voltas Limited", "face_val": "1", "subject": "Annual General Meeting And Dividend Rs.2.60 Per Share"}, {"object": "corp_action", "ex_date": "2015-07-10", "rec_date": null, "kind": "meeting", "factor": null, "div_per_share": null, "rights_ratio_n": null, "rights_ratio_m": null, "rights_premium": null, "series": "EQ", "isin": "INE226A01021", "comp": "Voltas Limited", "face_val": "1", "subject": "Annual General Meeting/Dividend - Rs 2.25/- Per Share"}, {"object": "corp_action", "ex_date": "2014-08-08", "rec_date": null, "kind": "meeting", "factor": null, "div_per_share": null, "rights_ratio_n": null, "rights_ratio_m": null, "rights_premium": null, "series": "EQ", "isin": "INE226A01021", "comp": "Voltas Limited", "face_val": "1", "subject": "Annual General Meeting / Dividend - Rs 1.60/- Per Share & Special Diamond Jubilee Dividend - Re 0.25/- Per Share"}, {"object": "corp_action", "ex_date": "2013-08-02", "rec_date": null, "kind": "meeting", "factor": null, "div_per_share": null, "rights_ratio_n": null, "rights_ratio_m": null, "rights_premium": null, "series": "EQ", "isin": "INE226A01021", "comp": "Voltas Limited", "face_val": "1", "subject": "Annual General Meeting / Dividend - Rs 1.60/- Per Share"}, {"object": "corp_action", "ex_date": "2012-08-01", "rec_date": null, "kind": "meeting", "factor": null, "div_per_share": null, "rights_ratio_n": null, "rights_ratio_m": null, "rights_premium": null, "series": "EQ", "isin": "INE226A01021", "comp": "Voltas Limited", "face_val": "1", "subject": "Annual General Meeting And Dividend Rs.1.60 Per Share"}, {"object": "corp_action", "ex_date": "2011-07-22", "rec_date": null, "kind": "meeting", "factor": null, "div_per_share": null, "rights_ratio_n": null, "rights_ratio_m": null, "rights_premium": null, "series": "EQ", "isin": "INE226A01021", "comp": "Voltas Limited", "face_val": "1", "subject": "Annual General Meeting And Dividend Rs.2/- Per Share"}, {"object": "corp_action", "ex_date": "2010-07-16", "rec_date": null, "kind": "meeting", "factor": null, "div_per_share": null, "rights_ratio_n": null, "rights_ratio_m": null, "rights_premium": null, "series": "EQ", "isin": "INE226A01021", "comp": "Voltas Limited", "face_val": "1", "subject": "Annual General Meeting And Dividend Rs.2/- Per Share"}, {"object": "corp_action", "ex_date": "2009-07-10", "rec_date": null, "kind": "meeting", "factor": null, "div_per_share": null, "rights_ratio_n": null, "rights_ratio_m": null, "rights_premium": null, "series": "EQ", "isin": "INE226A01021", "comp": "Voltas Limited", "face_val": "1", "subject": "Agm/Div-Rs.1.60 Per Share"}, {"object": "corp_action", "ex_date": "2008-06-27", "rec_date": null, "kind": "meeting", "factor": null, "div_per_share": null, "rights_ratio_n": null, "rights_ratio_m": null, "rights_premium": null, "series": "EQ", "isin": "INE226A01021", "comp": "Voltas Limited", "face_val": "1", "subject": "Agm/Dividend-135%"}, {"object": "corp_action", "ex_date": "2007-07-06", "rec_date": null, "kind": "meeting", "factor": null, "div_per_share": null, "rights_ratio_n": null, "rights_ratio_m": null, "rights_premium": null, "series": "EQ", "isin": "INE226A01021", "comp": "Voltas Limited", "face_val": "1", "subject": "Agm/Dividend-100%"}, {"object": "corp_action", "ex_date": "2006-09-22", "rec_date": "2006-09-29", "kind": "split", "factor": 10, "div_per_share": null, "rights_ratio_n": null, "rights_ratio_m": null, "rights_premium": null, "series": "EQ", "isin": "INE226A01021", "comp": "Voltas Limited", "face_val": "1", "subject": "Fv Split Rs.10/- To Re.1/"}, {"object": "corp_action", "ex_date": "2006-07-07", "rec_date": null, "kind": "meeting", "factor": null, "div_per_share": null, "rights_ratio_n": null, "rights_ratio_m": null, "rights_premium": null, "series": "EQ", "isin": "INE226A01021", "comp": "Voltas Limited", "face_val": "1", "subject": "Agm/Dividend-60%"}, {"object": "corp_action", "ex_date": "2005-07-29", "rec_date": null, "kind": "meeting", "factor": null, "div_per_share": null, "rights_ratio_n": null, "rights_ratio_m": null, "rights_premium": null, "series": "EQ", "isin": "INE226A01021", "comp": "Voltas Limited", "face_val": "1", "subject": "Agm/Div-(Fin-35%+Spl-15%)"}]